molmag_ac_gui/DataAnalysisTab.py
molmag_ac_gui/DataTableTab.py
molmag_ac_gui/DataTreatmentTab.py
molmag_ac_gui/__init__.py
molmag_ac_gui/__main__.py
molmag_ac_gui/ac_gui.py
molmag_ac_gui/dialogs.py
molmag_ac_gui/exceptions.py
molmag_ac_gui/layout.py
molmag_ac_gui/process_ac.py
molmag_ac_gui/utility.py
molmag_ac_gui/data/__init__.py
molmag_ac_gui/data/default_colormap.json
molmag_ac_gui/data/diamag_constants.json
molmag_ac_gui/data/read_options.json
molmag_ac_gui/data/styles.qss
molmag_ac_gui/data/tooltips.json
molmag_ac_gui-0.4.0.dist-info/LICENSE
molmag_ac_gui-0.4.0.dist-info/METADATA
molmag_ac_gui-0.4.0.dist-info/WHEEL
molmag_ac_gui-0.4.0.dist-info/top_level.txt
molmag_ac_gui-0.4.0.dist-info/RECORD
