Metadata-Version: 2.1
Name: molmag-ac-gui
Version: 0.4.0
Summary: A user interface and functions to work with magnetic relaxation
Home-page: http://www.eklahn.com
Author: Emil A. Klahn
Author-email: emil.klahn@gmail.com
License: MIT
Download-URL: https://pypi.org/project/molmag-ac-gui
Keywords: Magnetism,Molecular magnetism,Magnetic relaxation
Platform: UNKNOWN
License-File: LICENSE
